setup.cfg
setup.py
pyrstructs.egg-info/PKG-INFO
pyrstructs.egg-info/SOURCES.txt
pyrstructs.egg-info/dependency_links.txt
pyrstructs.egg-info/requires.txt
pyrstructs.egg-info/top_level.txt
rstructs/__init__.py
rstructs/rstructs.py