Metadata-Version: 1.0
Name: pyrstructs
Version: 0.1
Summary: Python data structures backed by Redis
Home-page: UNKNOWN
Author: merlin83
Author-email: UNKNOWN
License: BSD
Platform: UNKNOWN
